{"nodes": [{"id": "rawcv_components_creditbalance_tsx", "label": "CreditBalance.tsx", "file_type": "code", "source_file": "rawcv\\components\\CreditBalance.tsx", "source_location": "L1"}, {"id": "creditbalance_creditbalance", "label": "CreditBalance()", "file_type": "code", "source_file": "rawcv\\components\\CreditBalance.tsx", "source_location": "L12"}], "edges": [{"source": "rawcv_components_creditbalance_tsx", "target": "react", "relation": "imports_from", "confidence": "EXTRACTED", "source_file": "rawcv\\components\\CreditBalance.tsx", "source_location": "L3", "weight": 1.0}, {"source": "rawcv_components_creditbalance_tsx", "target": "link", "relation": "imports_from", "confidence": "EXTRACTED", "source_file": "rawcv\\components\\CreditBalance.tsx", "source_location": "L4", "weight": 1.0}, {"source": "rawcv_components_creditbalance_tsx", "target": "user_store", "relation": "imports_from", "confidence": "EXTRACTED", "source_file": "rawcv\\components\\CreditBalance.tsx", "source_location": "L5", "weight": 1.0}, {"source": "rawcv_components_creditbalance_tsx", "target": "creditbalance_creditbalance", "relation": "contains", "confidence": "EXTRACTED", "source_file": "rawcv\\components\\CreditBalance.tsx", "source_location": "L12", "weight": 1.0}], "raw_calls": [{"caller_nid": "creditbalance_creditbalance", "callee": "useState", "source_file": "rawcv\\components\\CreditBalance.tsx", "source_location": "L13"}, {"caller_nid": "creditbalance_creditbalance", "callee": "useState", "source_file": "rawcv\\components\\CreditBalance.tsx", "source_location": "L14"}, {"caller_nid": "creditbalance_creditbalance", "callee": "useEffect", "source_file": "rawcv\\components\\CreditBalance.tsx", "source_location": "L16"}]}